userhub_sdk/__init__.py
userhub_sdk/py.typed
userhub_sdk/_internal/__init__.py
userhub_sdk/_internal/constants.py
userhub_sdk/_internal/http_transport.py
userhub_sdk/_internal/request.py
userhub_sdk/_internal/response.py
userhub_sdk/_internal/test_transport.py
userhub_sdk/_internal/transport.py
userhub_sdk/_internal/util.py
userhub_sdk/adminapi/__init__.py
userhub_sdk/adminapi/_checkouts.py
userhub_sdk/adminapi/_client.py
userhub_sdk/adminapi/_flows.py
userhub_sdk/adminapi/_invoices.py
userhub_sdk/adminapi/_organizations.py
userhub_sdk/adminapi/_payment_methods.py
userhub_sdk/adminapi/_pricing.py
userhub_sdk/adminapi/_roles.py
userhub_sdk/adminapi/_subscriptions.py
userhub_sdk/adminapi/_users.py
userhub_sdk/adminv1/__init__.py
userhub_sdk/adminv1/_account_connection.py
userhub_sdk/adminv1/_account_connection_input.py
userhub_sdk/adminv1/_account_subscription.py
userhub_sdk/adminv1/_account_subscription_plan.py
userhub_sdk/adminv1/_account_subscription_product.py
userhub_sdk/adminv1/_account_subscription_seat.py
userhub_sdk/adminv1/_amazon_cognito_connection.py
userhub_sdk/adminv1/_auth0_connection.py
userhub_sdk/adminv1/_builtin_email_connection.py
userhub_sdk/adminv1/_card_payment_method.py
userhub_sdk/adminv1/_checkout.py
userhub_sdk/adminv1/_checkout_cancel_step.py
userhub_sdk/adminv1/_checkout_complete_payment_step.py
userhub_sdk/adminv1/_checkout_discount.py
userhub_sdk/adminv1/_checkout_input.py
userhub_sdk/adminv1/_checkout_item.py
userhub_sdk/adminv1/_checkout_item_input.py
userhub_sdk/adminv1/_checkout_step.py
userhub_sdk/adminv1/_checkout_trial_step.py
userhub_sdk/adminv1/_connection.py
userhub_sdk/adminv1/_connection_delegate.py
userhub_sdk/adminv1/_connection_provider.py
userhub_sdk/adminv1/_create_api_session_response.py
userhub_sdk/adminv1/_create_portal_session_response.py
userhub_sdk/adminv1/_flow.py
userhub_sdk/adminv1/_google_cloud_identity_platform_connection.py
userhub_sdk/adminv1/_invoice.py
userhub_sdk/adminv1/_invoice_account.py
userhub_sdk-0.8.2.dist-info/METADATA
userhub_sdk-0.8.2.dist-info/WHEEL
userhub_sdk-0.8.2.dist-info/licenses/LICENSE
userhub_sdk-0.8.2.dist-info/RECORD
