Metadata-Version: 2.4
Name: userhub-sdk
Version: 0.8.2
Summary: UserHub Python SDK
Project-URL: Homepage, https://userhub.com
Project-URL: Source, https://github.com/userhubdev/python-sdk
Author-email: UserHub <hello@userhub.com>
License-Expression: MIT
License-File: LICENSE
Classifier: Development Status :: 3 - Alpha
Classifier: Environment :: Web Environment
Classifier: Framework :: AsyncIO
Classifier: Framework :: Trio
Classifier: Intended Audience :: Developers
Classifier: License :: OSI Approved :: MIT License
Classifier: Operating System :: OS Independent
Classifier: Programming Language :: Python :: 3
Classifier: Programming Language :: Python :: 3 :: Only
Classifier: Programming Language :: Python :: 3.8
Classifier: Programming Language :: Python :: 3.9
Classifier: Programming Language :: Python :: 3.10
Classifier: Programming Language :: Python :: 3.11
Classifier: Programming Language :: Python :: 3.12
Requires-Python: >=3.8
Requires-Dist: httpcore<2,>=1
Provides-Extra: asyncio
Requires-Dist: httpcore[asyncio]; extra == 'asyncio'
Provides-Extra: trio
Requires-Dist: httpcore[trio]; extra == 'trio'
